fuit/__init__.py
fuit/codes/LoadCode.py
fuit/codes/__init__.py
fuit-1.4.dist-info/METADATA
fuit-1.4.dist-info/WHEEL
fuit-1.4.dist-info/top_level.txt
fuit-1.4.dist-info/RECORD
